README.md
setup.cfg
setup.py
mlozaic/__init__.py
mlozaic/colors.py
mlozaic/constants.py
mlozaic/grammar.py
mlozaic/leaves.py
mlozaic/operations.py
mlozaic/parser.py
mlozaic/renderer.py
mlozaic/sampler.py
mlozaic/transforms.py
mlozaic/value.py
mlozaic.egg-info/PKG-INFO
mlozaic.egg-info/SOURCES.txt
mlozaic.egg-info/dependency_links.txt
mlozaic.egg-info/entry_points.txt
mlozaic.egg-info/requires.txt
mlozaic.egg-info/top_level.txt
mlozaic/ast/__init__.py
mlozaic/ast/drawing.py
mlozaic/ast/expression.py
mlozaic/ast/node.py
mlozaic/dataset/__init__.py
mlozaic/dataset/standard_dataset.py